{
    "Сбер": {
        "Транспорт": 10.0,
        "Фастфуд": 5.0,
        "Хобби и развлечения": 5.0
    },
    "ВТБ": {
        "Все покупки": 2.0,
        "Кафе и рестораны": 3.0,
        "Такси": 5.0
    },
    "Озон": {
        "На все покупки": 1.0,
        "Аптеки": 5.0,
        "Одежда, обувь": 3.0,
        "Цветы": 5.0
    },
    "Альфа": {
        "За все покупки": 1.0,
        "Спортивные товары": 5.0,
        "Культура и искусство": 5.0
    },
    "Яндекс": {
        "Яндекс Плюс": 40.0,
        "Билеты на Кинопоиске": 25.0,
        "Бургер Кинг": 15.0,
        "Оплата телефоном": 2.0,
        "Городской транспорт": 10.0,
        "Книги": 20.0
    }
}